odoo/addons/product_exception/README.rst
odoo/addons/product_exception/__init__.py
odoo/addons/product_exception/__manifest__.py
odoo/addons/product_exception/data/data.xml
odoo/addons/product_exception/demo/product_exception.xml
odoo/addons/product_exception/i18n/it.po
odoo/addons/product_exception/i18n/product_exception.pot
odoo/addons/product_exception/models/__init__.py
odoo/addons/product_exception/models/exception_rule.py
odoo/addons/product_exception/models/product_product.py
odoo/addons/product_exception/models/product_template.py
odoo/addons/product_exception/readme/CONFIGURE.rst
odoo/addons/product_exception/readme/CONTRIBUTORS.rst
odoo/addons/product_exception/readme/DESCRIPTION.rst
odoo/addons/product_exception/readme/ROADMAP.rst
odoo/addons/product_exception/readme/USAGE.rst
odoo/addons/product_exception/static/description/icon.png
odoo/addons/product_exception/static/description/index.html
odoo/addons/product_exception/tests/__init__.py
odoo/addons/product_exception/tests/test_product_exception.py
odoo/addons/product_exception/views/exception_rule_views.xml
odoo/addons/product_exception/views/product_template_views.xml
odoo13_addon_product_exception-13.0.2.0.0.dist-info/METADATA
odoo13_addon_product_exception-13.0.2.0.0.dist-info/WHEEL
odoo13_addon_product_exception-13.0.2.0.0.dist-info/top_level.txt
odoo13_addon_product_exception-13.0.2.0.0.dist-info/RECORD
